signal_ICT_ManavChotai_92400133081/__init__.py
signal_ICT_ManavChotai_92400133081/operations.py
signal_ICT_ManavChotai_92400133081/trigonometric_signals.py
signal_ICT_ManavChotai_92400133081/unitary_signals.py
signal_ICT_ManavChotai_92400133081-1.0.0.dist-info/METADATA
signal_ICT_ManavChotai_92400133081-1.0.0.dist-info/WHEEL
signal_ICT_ManavChotai_92400133081-1.0.0.dist-info/top_level.txt
signal_ICT_ManavChotai_92400133081-1.0.0.dist-info/RECORD
