Metadata-Version: 2.1
Name: signal_ICT_ManavChotai_92400133081
Version: 1.0.0
Summary: A package for unitary, trigonometric signals and operations
Author: Manav Chotai
Requires-Dist: numpy
Requires-Dist: matplotlib
